<?xml version="1.0" encoding="UTF-8"?>
<!DOCTYPE level1 SYSTEM "history.dtd">
<level1 id="ko_078">
    <front>
        <biblioData type="초사류">
            <title>
                <mainTitle>三寶感應要略錄</mainTitle>
                <seriesTitle volume="">한국고대사료집성</seriesTitle>
            </title>
            <creator>
                <author>
                    <name align="center">비탁(非濁)</name>
                </author>
                <editor>
                    <name align="center"/>
                </editor>
            </creator>
            <publication>
                <publisher/>
            </publication>
            <holdings>
                <serialNumber callNo="223.4 고211대 v.49-52"/>
            </holdings>
            <source>
                <dateIssued>송대(宋代)</dateIssued>
            </source>
            <subjectClass level="1">자부</subjectClass>
            <subjectClass level="2">석가류</subjectClass>
        </biblioData>
        <description>
            <biblioExplanation id="ko_078_exp" name="三寶感應要略錄">
                <content>
                    <paragraph align="center">       　『三寶感應要略錄』은 宋나라 때의 승려 非濁이 여러 문헌들로부터 佛·法·僧의 三寶와 관련된 감응의 이야기들을 모아 편집한 책이다. 3권으로 구성되어 있으며, ‘佛寶聚’라는 이름의 上卷에는 佛像에 대한 감응담 50편, ‘法寶聚’라고 이름한 中卷에는 경전의 감응담 72편, ‘僧寶聚’라고 이름한 下卷에는 菩薩들이 감응하여 나타난 사례 42편이 수록되어 있다. 한국과 관련되는 내용으로는 新羅의 승려 僧兪가 처음에 阿含經을 소승이라고 하여 무시하였다가 꿈에 정토의 입구에서 無量天童子를 만나 가르침을 들은 후 이를 존중하여 정토에 왕생하였다는 이야기가 中卷에 나오고 있다. 신라시대의 정토신앙과 아함경에 대한 인식을 알게 하는 중요한 자료이다. 
                </paragraph>
                </content>
            </biblioExplanation>
        </description>
    </front>
    <level2 id="ko_078_0010">
        <front>
            <biblioData>
                <title>
                    <mainTitle>三寶感應要略錄</mainTitle>
                </title>
            </biblioData>
        </front>
        <level3 id="ko_078_0010_0010">
            <front>
                <biblioData>
                    <title>
                        <mainTitle>三寶感應要略錄 卷中, 第九 新羅僧兪誦阿含生淨土感應</mainTitle>
                    </title>
                    <subjectClass code="as04_01_02_01" scheme="주제">문화&gt;사상&gt;불교사상&gt;경논소</subjectClass>
                </biblioData>
            </front>
            <text>
                <content>
                    <paragraph align="center">○ <index type="서명">三寶感應要略錄</index> 卷中, 第九 <index type="국명">新羅</index>
                        <index type="이름">僧兪</index>誦阿含生淨土感應</paragraph>
                    <paragraph align="center">
                        <index type="국명">新羅</index>
                        <index type="이름">僧兪</index>者, <index type="국명">新羅</index>人也. 少出家, 歸心於淨土敎. 見諸誦持<index type="서명">阿含</index>者, 毁呵言捨, 夢至極樂東門, 將入門中. 爾時有<index type="이름">無量天</index>童子, 在門外立, 以寶杖驅出<index type="이름">兪</index>曰, 小道滅沒, 卽大敎滅相, 以小法爲梯撜登大道, 是汝國式也, 輕慢<index type="서명">阿含</index>捨不誦, 不可入大乘門云云. 夢覺悲泣悔過, 兼持誦<index type="서명">四阿含</index>, 得淨土迎, 弟子亦夢, 師坐蓮花, 來語曰, 我娑婆兼誦<index type="서명">阿含</index>, 依本習故, 先得小道, 不久還入大矣.</paragraph>
                </content>
            </text>
        </level3>
    </level2>
</level1>
